{
    "format_version": "1.8.0",
    "animations": {
        "animation.lantern_on_stick.third_person_main_hand": {
            "loop": true,
            "bones": {
                "root_x": {
                    "position": [0, 9, 0]
                }
            }
        },
        "animation.lantern_on_stick.third_person_off_hand": {
            "loop": true,
            "bones": {
                "root_x": {
                    "position": [0, 9, 0]
                }
            }
        },
        "animation.lantern_on_stick.first_person_main_hand": {
            "loop": true,
            "bones": {
                "root": {
                    "rotation": [90, 60, -10],
                    "position": [4, 7, 4],
                    "scale": 2
                }
            }
        },
        "animation.lantern_on_stick.first_person_off_hand": {
            "loop": true,
            "bones": {
                "root": {
                    "rotation": [90, 60, 10],
                    "position": [-4, 7, 4],
                    "scale": 2
                }
            }
        }
    }
}